first_mcp_server_src/__init__.py
first_mcp_server_src/main.py
first_mcp_server_src/py.typed
first_mcp_server_src-0.1.2.dist-info/METADATA
first_mcp_server_src-0.1.2.dist-info/WHEEL
first_mcp_server_src-0.1.2.dist-info/entry_points.txt
first_mcp_server_src-0.1.2.dist-info/RECORD
