Metadata-Version: 2.4
Name: first-mcp-server-src
Version: 0.1.2
Summary: Add your description here
Author-email: Sakthivel Chellapparimanam <srcsak@amazon.com>
Requires-Python: >=3.13
Requires-Dist: httpx>=0.28.1
Requires-Dist: mcp[cli]>=1.7.0
